{
  "resolution": "1280x720",
  "video_codec": "H264",
  "video_bitrate": 1000000,
  "frame_rate": 30,
  "video_layout": {
    "main": {
      "max_columns": 3,
      "video_sources": [
        "archive*.json"
      ]
    }
  },
  "video_toolbox_h264_encode_params": {
    "max_key_frame_interval": 300,
    "allow_frame_reordering": false,
    "prioritize_speed_over_quality": null,
    "real_time": null,
    "maximize_power_efficiency": null,
    "allow_temporal_compression": null,
    "profile_level": null,
    "h264_entropy_mode": null,
    "max_frame_delay_count": null,
    "use_parallelization": null
  }
}
